lizard_ui/__init__.py
lizard_ui/admin.py
lizard_ui/forms.py
lizard_ui/layout.py
lizard_ui/middleware.py
lizard_ui/models.py
lizard_ui/settingshelper.py
lizard_ui/tests.py
lizard_ui/testsettings.py
lizard_ui/uisettings.py
lizard_ui/urls.py
lizard_ui/views.py
lizard_ui/docs/__init__.html
lizard_ui/docs/admin.html
lizard_ui/docs/middleware.html
lizard_ui/docs/models.html
lizard_ui/docs/pycco.css
lizard_ui/docs/tests.html
lizard_ui/docs/testsettings.html
lizard_ui/docs/urls.html
lizard_ui/docs/views.html
lizard_ui/locale/af/LC_MESSAGES/django.mo
lizard_ui/locale/af/LC_MESSAGES/django.po
lizard_ui/locale/en/LC_MESSAGES/django.mo
lizard_ui/locale/en/LC_MESSAGES/django.po
lizard_ui/locale/nl/LC_MESSAGES/django.mo
lizard_ui/locale/nl/LC_MESSAGES/django.po
lizard_ui/locale/vi/LC_MESSAGES/django.mo
lizard_ui/locale/vi/LC_MESSAGES/django.po
lizard_ui/locale/zh/LC_MESSAGES/django.mo
lizard_ui/locale/zh/LC_MESSAGES/django.po
lizard_ui/management/__init__.py
lizard_ui/management/commands/__init__.py
lizard_ui/management/commands/i18n.py
lizard_ui/migrations/0001_initial.py
lizard_ui/migrations/__init__.py
lizard_ui/static/README.blueprint
lizard_ui/static/README.bootstrap
lizard_ui/static/README.colorpicker
lizard_ui/static/README.datatables
lizard_ui/static/README.daterangepicker.txt
lizard_ui/static/README.jquery
lizard_ui/static/README.jqueryui
lizard_ui/static/README.less
lizard_ui/static/README.openlayers
lizard_ui/static/README.sprites
lizard_ui/static/README.treeview
lizard_ui/static/blueprint/ie.css
lizard_ui/static/blueprint/print.css
lizard_ui/static/blueprint/screen.css
lizard_ui/static/blueprint/plugins/buttons/readme.txt
lizard_ui/static/blueprint/plugins/buttons/screen.css
lizard_ui/static/blueprint/plugins/buttons/icons/cross.png
lizard_ui/static/blueprint/plugins/buttons/icons/key.png
lizard_ui/static/blueprint/plugins/buttons/icons/tick.png
lizard_ui/static/blueprint/plugins/fancy-type/readme.txt
lizard_ui/static/blueprint/plugins/fancy-type/screen.css
lizard_ui-4.56.dist-info/LICENSE.rst
lizard_ui-4.56.dist-info/METADATA
lizard_ui-4.56.dist-info/WHEEL
lizard_ui-4.56.dist-info/top_level.txt
lizard_ui-4.56.dist-info/zip-safe
lizard_ui-4.56.dist-info/RECORD
