Metadata-Version: 2.1
Name: lizard-ui
Version: 4.56
Summary: Basic user interface for lizard websites
Home-page: http://www.nelen-schuurmans.nl/lizard/
Author: Reinout van Rees
Author-email: reinout.vanrees@nelen-schuurmans.nl
License: LGPL
Classifier: Programming Language :: Python
Classifier: Framework :: Django
License-File: LICENSE.rst
Requires-Dist: beautifulsoup4
Requires-Dist: Django <5,>=3.2
Requires-Dist: django-compressor >=1.1
Provides-Extra: test
Requires-Dist: nose ; extra == 'test'
Requires-Dist: coverage ; extra == 'test'
